MANIFEST.in
setup.py
ucla_cs118/__init__.py
ucla_cs118/pox.ice
ucla_cs118/pox_rpc_server.py
ucla_cs118.egg-info/PKG-INFO
ucla_cs118.egg-info/SOURCES.txt
ucla_cs118.egg-info/dependency_links.txt
ucla_cs118.egg-info/not-zip-safe
ucla_cs118.egg-info/top_level.txt