Metadata-Version: 1.1
Name: ucla-cs118
Version: 0.1.1
Summary: Network controller for the class project of UCLA CS118 class
Home-page: https://github.com/cs118/pox_rpc_server
Author: Alex Afanasyev
Author-email: aa@cs.ucla.edu
License: GPL3+
Platform: UNKNOWN
Classifier: License :: OSI Approved :: GNU General Public License (GPL)
Classifier: Programming Language :: Python
Classifier: Development Status :: 1 - Planning
Classifier: Intended Audience :: Developers
Classifier: Topic :: Internet
